{
	"prefabs": {
		"player": {
			"components": {
				"Transform": {
					"pos": { "x": 231, "y": 957 }
				}
			}
		},
		"enemy": {

		},
		"obstacle": {

		}
	},
	"scene": [
		{
			"name": "Player",
			"components": [
				{
					"type": "Transform",
					"pos": { "x": 450, "y": 850 },
					"scale": { "x": 1, "y": 1 }
				},
				{
					"type": "PlayerController",
					"speed": 200,
					"fire_rate": 1,
					"bullet_prefab": {
						"name": "Bullet",
						"components": [
							{
								"type": "Transform",
								"pos": { "x": 0, "y": 0 }
							},
							{
								"type": "Collider",
								"x": 6,
								"y": 15
							},
							{
								"type": "Rigidbody",
								"is_kinematic": false,
								"use_gravity": false,
								"velocity": {
									"x": 0,
									"y": -350
								}
							}
						]
					}
				},				
				{
					"type": "Sprite",
					"texture": "./sprites/spaceship.bmp"
				},
				{
					"type": "Collider",
					"x": 108,
					"y": 63
				},
				{
					"type": "Rigidbody",
					"is_kinematic": false,
					"use_gravity": false
				}
			]
		},
		{
			"name": "Invader",
			"row": 5,
			"col": 11,
			"width": 900,
			"height": 900,
			"components": [
				{
					"type": "Transform",
					"pos": { "x": 1, "y": 1 },
					"scale": { "x": 1, "y": 1 }
				},				
				{
					"type": "Sprite",
					"texture": "./sprites/invader.bmp"
				},
				{
					"type": "Collider",
					"x": 108,
					"y": 63
				},
				{
					"type": "Rigidbody",
					"is_kinematic": false,
					"use_gravity": false
				}
			]
		},
		{
			"name": "RightWall",
			"components": [
				{
					"type": "Transform",
					"pos": {
						"x": -5,
						"y": 450
					}
				},
				{
					"type": "Collider",
					"x": 10,
					"y": 900
				}
			]
		},
		{
			"name": "LeftWall",
			"components": [
				{
					"type": "Transform",
					"pos": {
						"x": 905,
						"y": 450
					}
				},
				{
					"type": "Collider",
					"x": 10,
					"y": 900
				}
			]
		}
	]
}